LICENSE
README.md
setup.py
pyllmkit/__init__.py
pyllmkit.egg-info/PKG-INFO
pyllmkit.egg-info/SOURCES.txt
pyllmkit.egg-info/dependency_links.txt
pyllmkit.egg-info/top_level.txt
pyllmkit/api/__init__.py
pyllmkit/api/spark.py
pyllmkit/web/__init__.py
pyllmkit/web/webui.py