Metadata-Version: 2.1
Name: pyllmkit
Version: 0.0.1
Summary: pyllmkit
Home-page: http://www.52phm.cn
Author: 52phm
Author-email: 2374521450@qq.com
License: Apache License 2
Project-URL: Homepage, http://www.52phm.cn
Project-URL: Bug Tracker, https://github.com/pypa/sampleproject/issues
Project-URL: Download, http://www.52phm.cn
Project-URL: Documentation, http://www.52phm.cn
Project-URL: Source Code, http://www.52phm.cn
Project-URL: 主页(Homepage), http://www.52phm.cn
Project-URL: 文档(Documentation), http://www.52phm.cn
License-File: LICENSE
